kog/__init__.py
kog-0.0.1.dist-info/METADATA
kog-0.0.1.dist-info/WHEEL
kog-0.0.1.dist-info/top_level.txt
kog-0.0.1.dist-info/RECORD
